[
  {
    "date": "5/12 盛岡 1R",
    "venue": "盛岡",
    "raceNum": "1R",
    "raceClass": "C2三組",
    "winner": 9,
    "winOdds": 17.4,
    "hit": false,
    "sm_temperature": 22,
    "sm_minpct": 3,
    "ev_min": 100,
    "ev_max": null,
    "odds_min": null,
    "odds_max": 150,
    "kelly_fraction": 0.5,
    "records": [
      {
        "num": 3,
        "name": "ロッサヴィール",
        "norm": 0.2629,
        "tanOdds": 8.7,
        "ev": 228.7,
        "isWinner": false,
        "isBet": true,
        "payout": null
      },
      {
        "num": 6,
        "name": "エスカペード",
        "norm": 0.1198,
        "tanOdds": 16.1,
        "ev": 192.8,
        "isWinner": false,
        "isBet": true,
        "payout": null
      },
      {
        "num": 5,
        "name": "バスターショット",
        "norm": 0.0306,
        "tanOdds": 108.2,
        "ev": 331.3,
        "isWinner": false,
        "isBet": true,
        "payout": null
      }
    ],
    "savedAt": "2026-05-12T22:10:20.640Z"
  },
  {
    "date": "5/12 盛岡 2R",
    "venue": "盛岡",
    "raceNum": "2R",
    "raceClass": "C2二組",
    "winner": 2,
    "winOdds": 3.6,
    "hit": false,
    "sm_temperature": 22,
    "sm_minpct": 3,
    "ev_min": 100,
    "ev_max": null,
    "odds_min": null,
    "odds_max": 150,
    "kelly_fraction": 0.5,
    "records": [
      {
        "num": 7,
        "name": "テーオーカバリエ",
        "norm": 0.2114,
        "tanOdds": 6.9,
        "ev": 145.9,
        "isWinner": false,
        "isBet": true,
        "payout": null
      },
      {
        "num": 1,
        "name": "カールルイコ",
        "norm": 0.0682,
        "tanOdds": 26.9,
        "ev": 183.4,
        "isWinner": false,
        "isBet": true,
        "payout": null
      },
      {
        "num": 8,
        "name": "シラユリ",
        "norm": 0.0553,
        "tanOdds": 18.4,
        "ev": 101.8,
        "isWinner": false,
        "isBet": true,
        "payout": null
      },
      {
        "num": 6,
        "name": "モレッキ",
        "norm": 0.0478,
        "tanOdds": 21.4,
        "ev": 102.3,
        "isWinner": false,
        "isBet": true,
        "payout": null
      }
    ],
    "savedAt": "2026-05-12T22:12:04.454Z"
  },
  {
    "date": "5/12 盛岡 3R",
    "venue": "盛岡",
    "raceNum": "3R",
    "raceClass": "C2一組",
    "winner": 4,
    "winOdds": 1.2,
    "hit": false,
    "sm_temperature": 22,
    "sm_minpct": 3,
    "ev_min": 100,
    "ev_max": null,
    "odds_min": null,
    "odds_max": 150,
    "kelly_fraction": 0.5,
    "records": [
      {
        "num": 1,
        "name": "フクチャンサクラ",
        "norm": 0.2544,
        "tanOdds": 6.3,
        "ev": 160.3,
        "isWinner": false,
        "isBet": true,
        "payout": null
      },
      {
        "num": 3,
        "name": "エコセーズ",
        "norm": 0.0923,
        "tanOdds": 16.2,
        "ev": 149.5,
        "isWinner": false,
        "isBet": true,
        "payout": null
      },
      {
        "num": 2,
        "name": "シャイニーメイン",
        "norm": 0.0132,
        "tanOdds": 86.5,
        "ev": 114.1,
        "isWinner": false,
        "isBet": true,
        "payout": null
      }
    ],
    "savedAt": "2026-05-12T22:13:30.756Z"
  },
  {
    "date": "5/12 盛岡 4R",
    "venue": "盛岡",
    "raceNum": "4R",
    "raceClass": "C1",
    "winner": 4,
    "winOdds": 2.5,
    "hit": false,
    "sm_temperature": 22,
    "sm_minpct": 3,
    "ev_min": 100,
    "ev_max": null,
    "odds_min": null,
    "odds_max": 150,
    "kelly_fraction": 0.5,
    "records": [
      {
        "num": 1,
        "name": "ヤマニンエピクーレ",
        "norm": 0.2375,
        "tanOdds": 9.3,
        "ev": 220.9,
        "isWinner": false,
        "isBet": true,
        "payout": null
      },
      {
        "num": 8,
        "name": "テーオーシュターデ",
        "norm": 0.1666,
        "tanOdds": 10.5,
        "ev": 174.9,
        "isWinner": false,
        "isBet": true,
        "payout": null
      },
      {
        "num": 10,
        "name": "ベロニカブレイン",
        "norm": 0.089,
        "tanOdds": 84.6,
        "ev": 752.7,
        "isWinner": false,
        "isBet": true,
        "payout": null
      },
      {
        "num": 5,
        "name": "リーガルスピード",
        "norm": 0.0862,
        "tanOdds": 19.4,
        "ev": 167.2,
        "isWinner": false,
        "isBet": true,
        "payout": null
      }
    ],
    "savedAt": "2026-05-12T22:15:01.768Z"
  },
  {
    "date": "5/12 盛岡 5R",
    "venue": "盛岡",
    "raceNum": "5R",
    "raceClass": "C1",
    "winner": 2,
    "winOdds": 1.8,
    "hit": false,
    "sm_temperature": 22,
    "sm_minpct": 3,
    "ev_min": 100,
    "ev_max": null,
    "odds_min": null,
    "odds_max": 150,
    "kelly_fraction": 0.5,
    "records": [
      {
        "num": 11,
        "name": "ネコニコタツ",
        "norm": 0.1588,
        "tanOdds": 18.5,
        "ev": 293.8,
        "isWinner": false,
        "isBet": true,
        "payout": null
      },
      {
        "num": 4,
        "name": "キタノブルーアレツ",
        "norm": 0.1581,
        "tanOdds": 8.7,
        "ev": 137.6,
        "isWinner": false,
        "isBet": true,
        "payout": null
      },
      {
        "num": 3,
        "name": "スリアント",
        "norm": 0.0796,
        "tanOdds": 17.4,
        "ev": 138.5,
        "isWinner": false,
        "isBet": true,
        "payout": null
      },
      {
        "num": 10,
        "name": "エイカイソフィア",
        "norm": 0.0466,
        "tanOdds": 47.6,
        "ev": 221.6,
        "isWinner": false,
        "isBet": true,
        "payout": null
      }
    ],
    "savedAt": "2026-05-12T22:16:19.336Z"
  },
  {
    "date": "5/12 盛岡 6R",
    "venue": "盛岡",
    "raceNum": "6R",
    "raceClass": "C1",
    "winner": 6,
    "winOdds": 1.3,
    "hit": false,
    "sm_temperature": 22,
    "sm_minpct": 3,
    "ev_min": 100,
    "ev_max": null,
    "odds_min": null,
    "odds_max": 150,
    "kelly_fraction": 0.5,
    "records": [
      {
        "num": 5,
        "name": "タナキーボー",
        "norm": 0.1631,
        "tanOdds": 6.3,
        "ev": 102.8,
        "isWinner": false,
        "isBet": true,
        "payout": null
      },
      {
        "num": 3,
        "name": "シノブデスティーノ",
        "norm": 0.1114,
        "tanOdds": 14.3,
        "ev": 159.2,
        "isWinner": false,
        "isBet": true,
        "payout": null
      },
      {
        "num": 8,
        "name": "パンディーロ",
        "norm": 0.0467,
        "tanOdds": 21.8,
        "ev": 101.9,
        "isWinner": false,
        "isBet": true,
        "payout": null
      },
      {
        "num": 7,
        "name": "セジールレーヴ",
        "norm": 0.0326,
        "tanOdds": 74,
        "ev": 241.5,
        "isWinner": false,
        "isBet": true,
        "payout": null
      }
    ],
    "savedAt": "2026-05-12T22:17:52.754Z"
  },
  {
    "date": "5/12 盛岡 7R",
    "venue": "盛岡",
    "raceNum": "7R",
    "raceClass": "C1",
    "winner": 8,
    "winOdds": 4.3,
    "hit": false,
    "sm_temperature": 22,
    "sm_minpct": 3,
    "ev_min": 100,
    "ev_max": null,
    "odds_min": null,
    "odds_max": 150,
    "kelly_fraction": 0.5,
    "records": [
      {
        "num": 7,
        "name": "ヒロスズラン",
        "norm": 0.3006,
        "tanOdds": 6.7,
        "ev": 201.4,
        "isWinner": false,
        "isBet": true,
        "payout": null
      },
      {
        "num": 2,
        "name": "レーヌデゼトワール",
        "norm": 0.1513,
        "tanOdds": 12.9,
        "ev": 195.2,
        "isWinner": false,
        "isBet": true,
        "payout": null
      },
      {
        "num": 4,
        "name": "ヤマショウシャイン",
        "norm": 0.1033,
        "tanOdds": 15.2,
        "ev": 157,
        "isWinner": false,
        "isBet": true,
        "payout": null
      },
      {
        "num": 5,
        "name": "ジュレヴァー",
        "norm": 0.0613,
        "tanOdds": 29,
        "ev": 177.6,
        "isWinner": false,
        "isBet": true,
        "payout": null
      }
    ],
    "savedAt": "2026-05-12T22:19:13.264Z"
  },
  {
    "date": "5/12 盛岡 8R",
    "venue": "盛岡",
    "raceNum": "8R",
    "raceClass": "C1",
    "winner": 1,
    "winOdds": 2,
    "hit": false,
    "sm_temperature": 22,
    "sm_minpct": 3,
    "ev_min": 100,
    "ev_max": null,
    "odds_min": null,
    "odds_max": 150,
    "kelly_fraction": 0.5,
    "records": [
      {
        "num": 8,
        "name": "カイトリヒト",
        "norm": 0.1285,
        "tanOdds": 28.4,
        "ev": 365,
        "isWinner": false,
        "isBet": true,
        "payout": null
      },
      {
        "num": 6,
        "name": "ネイチャーミヤビ",
        "norm": 0.0944,
        "tanOdds": 12.2,
        "ev": 115.1,
        "isWinner": false,
        "isBet": true,
        "payout": null
      },
      {
        "num": 10,
        "name": "エルモドーロ",
        "norm": 0.0624,
        "tanOdds": 66.3,
        "ev": 413.7,
        "isWinner": false,
        "isBet": true,
        "payout": null
      },
      {
        "num": 7,
        "name": "ヤマニンファリダ",
        "norm": 0.0513,
        "tanOdds": 26.4,
        "ev": 135.5,
        "isWinner": false,
        "isBet": true,
        "payout": null
      }
    ],
    "savedAt": "2026-05-12T22:20:38.910Z"
  },
  {
    "date": "5/12 盛岡 9R",
    "venue": "盛岡",
    "raceNum": "9R",
    "raceClass": "C1",
    "winner": 8,
    "winOdds": 2.9,
    "hit": false,
    "sm_temperature": 22,
    "sm_minpct": 3,
    "ev_min": 100,
    "ev_max": null,
    "odds_min": null,
    "odds_max": 150,
    "kelly_fraction": 0.5,
    "records": [
      {
        "num": 2,
        "name": "コンバットスプーン",
        "norm": 0.3974,
        "tanOdds": 2.6,
        "ev": 103.3,
        "isWinner": false,
        "isBet": true,
        "payout": null
      },
      {
        "num": 10,
        "name": "プレイフルネス",
        "norm": 0.1197,
        "tanOdds": 20.3,
        "ev": 243,
        "isWinner": false,
        "isBet": true,
        "payout": null
      },
      {
        "num": 4,
        "name": "ヴィオレーヌ",
        "norm": 0.056,
        "tanOdds": 23.5,
        "ev": 131.7,
        "isWinner": false,
        "isBet": true,
        "payout": null
      },
      {
        "num": 5,
        "name": "フタイテンホイール",
        "norm": 0.0395,
        "tanOdds": 66.1,
        "ev": 261,
        "isWinner": false,
        "isBet": true,
        "payout": null
      }
    ],
    "savedAt": "2026-05-12T22:21:57.019Z"
  },
  {
    "date": "5/12 盛岡 10",
    "venue": "盛岡",
    "raceNum": "10R",
    "raceClass": "C1",
    "winner": 6,
    "winOdds": 1.7,
    "hit": false,
    "sm_temperature": 22,
    "sm_minpct": 3,
    "ev_min": 100,
    "ev_max": null,
    "odds_min": null,
    "odds_max": 150,
    "kelly_fraction": 0.5,
    "records": [
      {
        "num": 2,
        "name": "ピースワンジョケル",
        "norm": 0.1186,
        "tanOdds": 14.2,
        "ev": 168.4,
        "isWinner": false,
        "isBet": true,
        "payout": null
      },
      {
        "num": 9,
        "name": "インディーフィルム",
        "norm": 0.0945,
        "tanOdds": 17.4,
        "ev": 164.4,
        "isWinner": false,
        "isBet": true,
        "payout": null
      },
      {
        "num": 10,
        "name": "エターナルルビー",
        "norm": 0.06,
        "tanOdds": 24.7,
        "ev": 148.1,
        "isWinner": false,
        "isBet": true,
        "payout": null
      },
      {
        "num": 7,
        "name": "アイスボウル",
        "norm": 0.032,
        "tanOdds": 38.4,
        "ev": 123,
        "isWinner": false,
        "isBet": true,
        "payout": null
      }
    ],
    "savedAt": "2026-05-12T22:23:10.136Z"
  },
  {
    "date": "5/12 盛岡 11",
    "venue": "盛岡",
    "raceNum": "11R",
    "raceClass": "ハヤテ特別OP",
    "winner": 11,
    "winOdds": 8.6,
    "hit": false,
    "sm_temperature": 22,
    "sm_minpct": 3,
    "ev_min": 100,
    "ev_max": null,
    "odds_min": null,
    "odds_max": 150,
    "kelly_fraction": 0.5,
    "records": [
      {
        "num": 4,
        "name": "バトルバーリライ",
        "norm": 0.2174,
        "tanOdds": 7.2,
        "ev": 156.6,
        "isWinner": false,
        "isBet": true,
        "payout": null
      },
      {
        "num": 8,
        "name": "メイショウイジゲン",
        "norm": 0.0999,
        "tanOdds": 19,
        "ev": 189.9,
        "isWinner": false,
        "isBet": true,
        "payout": null
      },
      {
        "num": 3,
        "name": "ビップアクア",
        "norm": 0.0959,
        "tanOdds": 25.3,
        "ev": 242.7,
        "isWinner": false,
        "isBet": true,
        "payout": null
      },
      {
        "num": 5,
        "name": "リリーコレール",
        "norm": 0.0845,
        "tanOdds": 15.4,
        "ev": 130.1,
        "isWinner": false,
        "isBet": true,
        "payout": null
      }
    ],
    "savedAt": "2026-05-12T22:24:37.285Z"
  },
  {
    "date": "5/12 盛岡 12",
    "venue": "盛岡",
    "raceNum": "12R",
    "raceClass": "スプリント特別OP",
    "winner": 1,
    "winOdds": 48.3,
    "hit": false,
    "sm_temperature": 22,
    "sm_minpct": 3,
    "ev_min": 100,
    "ev_max": null,
    "odds_min": null,
    "odds_max": 150,
    "kelly_fraction": 0.5,
    "records": [
      {
        "num": 8,
        "name": "ベストリーガード",
        "norm": 0.1475,
        "tanOdds": 21.4,
        "ev": 315.6,
        "isWinner": false,
        "isBet": true,
        "payout": null
      },
      {
        "num": 9,
        "name": "シンヨモギネス",
        "norm": 0.0862,
        "tanOdds": 12.1,
        "ev": 104.4,
        "isWinner": false,
        "isBet": true,
        "payout": null
      },
      {
        "num": 7,
        "name": "スターシューター",
        "norm": 0.0581,
        "tanOdds": 18.2,
        "ev": 105.7,
        "isWinner": false,
        "isBet": true,
        "payout": null
      },
      {
        "num": 11,
        "name": "ポマイカイ",
        "norm": 0.0407,
        "tanOdds": 99.3,
        "ev": 404.5,
        "isWinner": false,
        "isBet": true,
        "payout": null
      }
    ],
    "savedAt": "2026-05-12T22:26:08.408Z"
  },
  {
    "date": "5/10 新潟 1R",
    "venue": "新潟",
    "raceNum": "1R",
    "raceClass": "3歳未勝利",
    "winner": 14,
    "winOdds": 6.8,
    "hit": true,
    "sm_temperature": 22,
    "sm_minpct": 3,
    "ev_min": 100,
    "ev_max": null,
    "odds_min": null,
    "odds_max": 150,
    "kelly_fraction": 0.5,
    "records": [
      {
        "num": 1,
        "name": "ロココ",
        "norm": 0.15,
        "tanOdds": 15.2,
        "ev": 228,
        "isWinner": false,
        "isBet": true,
        "payout": null
      },
      {
        "num": 14,
        "name": "フローラルウェイ",
        "norm": 0.0326,
        "tanOdds": 79.5,
        "ev": 258.9,
        "isWinner": true,
        "isBet": true,
        "payout": 6.8
      },
      {
        "num": 10,
        "name": "アルデナイン",
        "norm": 0.0283,
        "tanOdds": 68.6,
        "ev": 194.1,
        "isWinner": false,
        "isBet": true,
        "payout": null
      },
      {
        "num": 15,
        "name": "ボヤージュブルー",
        "norm": 0.0267,
        "tanOdds": 75.2,
        "ev": 200.5,
        "isWinner": false,
        "isBet": true,
        "payout": null
      }
    ],
    "savedAt": "2026-05-12T22:27:30.369Z"
  },
  {
    "date": "5/10 新潟 2R",
    "venue": "新潟",
    "raceNum": "2R",
    "raceClass": "3歳未勝利",
    "winner": 7,
    "winOdds": 5,
    "hit": false,
    "sm_temperature": 22,
    "sm_minpct": 3,
    "ev_min": 100,
    "ev_max": null,
    "odds_min": null,
    "odds_max": 150,
    "kelly_fraction": 0.5,
    "records": [
      {
        "num": 14,
        "name": "フェルアフリーゼ",
        "norm": 0.1127,
        "tanOdds": 14.7,
        "ev": 165.7,
        "isWinner": false,
        "isBet": true,
        "payout": null
      },
      {
        "num": 3,
        "name": "ベセル",
        "norm": 0.0983,
        "tanOdds": 10.9,
        "ev": 107.2,
        "isWinner": false,
        "isBet": true,
        "payout": null
      },
      {
        "num": 6,
        "name": "セントリアン",
        "norm": 0.082,
        "tanOdds": 18.3,
        "ev": 150,
        "isWinner": false,
        "isBet": true,
        "payout": null
      },
      {
        "num": 12,
        "name": "アイアンナックル",
        "norm": 0.0422,
        "tanOdds": 37.4,
        "ev": 157.9,
        "isWinner": false,
        "isBet": true,
        "payout": null
      }
    ],
    "savedAt": "2026-05-12T22:27:51.839Z"
  },
  {
    "date": "5/10 新潟 3R",
    "venue": "新潟",
    "raceNum": "3R",
    "raceClass": "3歳未勝利",
    "winner": 5,
    "winOdds": 90.1,
    "hit": true,
    "sm_temperature": 22,
    "sm_minpct": 3,
    "ev_min": 100,
    "ev_max": null,
    "odds_min": null,
    "odds_max": 150,
    "kelly_fraction": 0.5,
    "records": [
      {
        "num": 5,
        "name": "ノリノドラゴン",
        "norm": 0.1219,
        "tanOdds": 8.7,
        "ev": 106.1,
        "isWinner": true,
        "isBet": true,
        "payout": 90.1
      },
      {
        "num": 8,
        "name": "ウインガネーシャ",
        "norm": 0.0436,
        "tanOdds": 32.8,
        "ev": 143.2,
        "isWinner": false,
        "isBet": true,
        "payout": null
      },
      {
        "num": 11,
        "name": "ヤマタケボニータ",
        "norm": 0.0343,
        "tanOdds": 53.4,
        "ev": 183.2,
        "isWinner": false,
        "isBet": true,
        "payout": null
      },
      {
        "num": 6,
        "name": "メイショウイッカク",
        "norm": 0.0326,
        "tanOdds": 43.9,
        "ev": 143.2,
        "isWinner": false,
        "isBet": true,
        "payout": null
      }
    ],
    "savedAt": "2026-05-12T22:28:13.170Z"
  }
]